gui/__init__.py
gui/gui.py
tas/__init__.py
tas/constants.py
tas/playback.py
tas/recorder.py
tas/utils.py
tas_recorder-1.1.0.dist-info/LICENSE
tas_recorder-1.1.0.dist-info/METADATA
tas_recorder-1.1.0.dist-info/WHEEL
tas_recorder-1.1.0.dist-info/top_level.txt
tas_recorder-1.1.0.dist-info/RECORD
